aiogram_mg_handler/__init__.py
aiogram_mg_handler/handler.py
aiogram_mg_handler/storages/__init__.py
aiogram_mg_handler/storages/base.py
aiogram_mg_handler/storages/memory.py
aiogram_mg_handler/storages/mongo.py
aiogram_mg_handler/storages/redis.py
aiogram_mg_handler-0.7.dist-info/METADATA
aiogram_mg_handler-0.7.dist-info/WHEEL
aiogram_mg_handler-0.7.dist-info/top_level.txt
aiogram_mg_handler-0.7.dist-info/RECORD
