Metadata-Version: 2.1
Name: aiogram-mg-handler
Version: 0.7
Summary: Aiogram media group handler. Fork of aiogram-media-group
Author: crut0i
Keywords: aiogram handler
Classifier: Programming Language :: Python :: 3
Classifier: License :: OSI Approved :: MIT License
Classifier: Operating System :: OS Independent
Requires-Python: >=3.0
Requires-Dist: aiogram
Requires-Dist: aioredis
Requires-Dist: motor
Requires-Dist: ujson
